access_control/__init__.py
access_control/s3_access_control_plugin.py
vijay_access_control-0.2.dist-info/METADATA
vijay_access_control-0.2.dist-info/WHEEL
vijay_access_control-0.2.dist-info/top_level.txt
vijay_access_control-0.2.dist-info/RECORD
