Metadata-Version: 2.1
Name: vijay-access-control
Version: 0.2
Summary: s3 access control package
